{
  "summary": "Phase 3: Implement Ghost Content API to power the blog index and article pages.",
  "files": [
    {
      "file_path": "app/globals.css",
      "code_diff": "<<<<<<< SEARCH\n@import \"tailwindcss\";\n\n:root {\n=======\n@import \"tailwindcss\";\n@import \"@tailwindcss/typography\";\n\n:root {\n>>>>>>> REPLACE"
    },
    {
      "file_path": "lib/ghost.ts",
      "code_diff": "<<<<<<< SEARCH\n=======\nimport GhostContentAPI from '@tryghost/content-api';\n\nconst url = process.env.GHOST_URL;\nconst key = process.env.GHOST_CONTENT_API_KEY;\n\nif (!url || !key) {\n  throw new Error(\n    'GHOST_URL and GHOST_CONTENT_API_KEY are required environment variables. Please check your .env.local file.'\n  );\n}\n\n// Create API instance with site credentials\nconst api = new GhostContentAPI({\n  url,\n  key,\n  version: 'v5.0',\n});\n\nexport default api;\n>>>>>>> REPLACE"
    },
    {
      "file_path": "app/blog/page.tsx",
      "code_diff": "<<<<<<< SEARCH\nexport default function BlogIndex() {\n  return (\n    <div className=\"container mx-auto px-4 py-24\">\n      <h1 className=\"text-4xl font-bold tracking-tighter mb-6\">Safety Blog</h1>\n      <p className=\"text-lg text-muted-foreground mb-12\">\n        [Ghost Blog Index Placeholder] - This route (&quot;/blog&quot;) will fetch the latest articles, tags, and authors from the Ghost Content API.\n      </p>\n      <div className=\"grid grid-cols-1 md:grid-cols-2 lg:grid-cols-3 gap-8\">\n        {/* Placeholder Cards */}\n        {[1, 2, 3].map((i) => (\n          <div key={i} className=\"rounded-lg border border-border bg-card p-6 shadow-sm\">\n            <div className=\"h-48 bg-muted rounded-md mb-4\" />\n            <h2 className=\"text-xl font-semibold mb-2\">Sample Article {i}</h2>\n            <p className=\"text-muted-foreground text-sm\">A brief excerpt of the safety article will appear here. Sourced from Ghost.</p>\n          </div>\n        ))}\n      </div>\n    </div>\n  );\n}\n=======\nimport ghost from \"@/lib/ghost\";\nimport type { PostOrPage } from \"@tryghost/content-api\";\nimport Link from \"next/link\";\nimport Image from 'next/image';\n\nasync function getPosts() {\n  try {\n    return await ghost.posts.browse({\n      limit: 'all',\n      include: ['tags', 'authors'],\n    });\n  } catch (error) {\n    console.error(\"Failed to fetch posts from Ghost:\", error);\n    return [];\n  }\n}\n\nfunction BlogCard({ post }: { post: PostOrPage }) {\n  const postDate = new Date(post.published_at || new Date()).toLocaleDateString('en-US', {\n    year: 'numeric',\n    month: 'long',\n    day: 'numeric',\n  });\n\n  return (\n    <Link href={`/blog/${post.slug}`} className=\"flex flex-col rounded-lg border border-border bg-card shadow-sm transition-shadow hover:shadow-md\">\n      {post.feature_image && (\n        <div className=\"relative h-48 w-full\">\n            <Image\n                src={post.feature_image}\n                alt={post.feature_image_alt || post.title || 'Blog post image'}\n                fill\n                sizes=\"(max-width: 768px) 100vw, (max-width: 1200px) 50vw, 33vw\"\n                className=\"rounded-t-lg object-cover\"\n            />\n        </div>\n      )}\n      <div className=\"p-6 flex-1 flex flex-col\">\n        <h2 className=\"text-xl font-semibold mb-2 leading-snug\">{post.title}</h2>\n        <p className=\"text-muted-foreground text-sm mb-4 flex-1\">{post.excerpt}</p>\n        <div className=\"text-xs text-muted-foreground mt-auto pt-4 border-t border-border\">\n            <span>{post.authors?.[0]?.name}</span> &bull; <span>{postDate}</span>\n        </div>\n      </div>\n    </Link>\n  );\n}\n\nexport default async function BlogIndex() {\n  const posts = await getPosts();\n\n  return (\n    <div className=\"container mx-auto px-4 py-24\">\n      <h1 className=\"text-4xl font-bold tracking-tighter mb-6\">Safety Blog</h1>\n      <p className=\"text-lg text-muted-foreground mb-12\">\n        Insights and updates on safety compliance and best practices.\n      </p>\n      {posts.length > 0 ? (\n        <div className=\"grid grid-cols-1 md:grid-cols-2 lg:grid-cols-3 gap-8\">\n          {posts.map((post) => (\n            <BlogCard key={post.id} post={post} />\n          ))}\n        </div>\n      ) : (\n        <p className=\"text-center text-muted-foreground\">No articles found. Please check the Ghost integration.</p>\n      )}\n    </div>\n  );\n}\n>>>>>>> REPLACE"
    },
    {
      "file_path": "app/blog/[slug]/page.tsx",
      "code_diff": "<<<<<<< SEARCH\ntype Props = {\n  params: Promise<{ slug: string }>;\n};\n\nexport default async function BlogPost({ params }: Props) {\n  const { slug } = await params;\n\n  return (\n    <article className=\"container mx-auto px-4 py-24 max-w-3xl\">\n      <header className=\"mb-12 text-center\">\n        <h1 className=\"text-4xl font-bold tracking-tighter mb-4 capitalize\">{slug.replace(/-/g, ' ')}</h1>\n        <p className=\"text-muted-foreground\">Published on Ghost • By Safety Expert</p>\n      </header>\n      <div className=\"prose prose-slate dark:prose-invert max-w-none\">\n        <p className=\"text-lg text-muted-foreground\">\n          [Ghost Article Placeholder] - This route (&quot;/blog/{slug}&quot;) will fetch the specific blog post content and metadata from the Ghost Content API.\n        </p>\n      </div>\n    </article>\n  );\n}\n=======\nimport ghost from \"@/lib/ghost\";\nimport { sanitizeHtmlForDangerouslySetInnerHTML } from \"@/lib/utils\";\nimport { notFound } from \"next/navigation\";\nimport type { PostOrPage } from \"@tryghost/content-api\";\n\nasync function getPost(slug: string): Promise<PostOrPage | null> {\n  try {\n    return await ghost.posts.read(\n      { slug }, \n      { include: ['authors', 'tags'] }\n    );\n  } catch (error) {\n    console.error(`Failed to fetch post with slug '${slug}':`, error);\n    return null;\n  }\n}\n\n// Pre-build all blog pages for performance\nexport async function generateStaticParams() {\n  const posts = await ghost.posts.browse({ limit: 'all', fields: 'slug' });\n  return posts.map((post) => ({ slug: post.slug }));\n}\n\ntype Props = {\n  params: { slug: string };\n};\n\nexport default async function BlogPost({ params }: Props) {\n  const post = await getPost(params.slug);\n\n  if (!post) {\n    return notFound();\n  }\n\n  const postDate = new Date(post.published_at || new Date()).toLocaleDateString('en-US', {\n    year: 'numeric',\n    month: 'long',\n    day: 'numeric',\n  });\n\n  const sanitizedHtml = sanitizeHtmlForDangerouslySetInnerHTML(post.html);\n\n  return (\n    <article className=\"container mx-auto px-4 py-24 max-w-3xl\">\n      <header className=\"mb-12 text-center\">\n        <h1 className=\"text-4xl font-bold tracking-tighter mb-4\">{post.title}</h1>\n        <p className=\"text-muted-foreground\">\n          Published on {postDate} • By {post.authors?.[0]?.name || 'Safety Expert'}\n        </p>\n      </header>\n      <div\n        className=\"prose prose-slate dark:prose-invert max-w-none\"\n        dangerouslySetInnerHTML={{ __html: sanitizedHtml }}\n      />\n    </article>\n  );\n}\n>>>>>>> REPLACE"
    }
  ]
}
